asyncuvkit/__init__.py
asyncuvkit/asyncuvkit2.cp311-win_amd64.pyd
asyncuvkit-0.6.5.dist-info/METADATA
asyncuvkit-0.6.5.dist-info/WHEEL
asyncuvkit-0.6.5.dist-info/top_level.txt
asyncuvkit-0.6.5.dist-info/RECORD
