Metadata-Version: 2.4
Name: asyncuvkit
Version: 0.6.5
Summary: Asyncuvkit
Author-email: Asyncuvkit <asyncuvkit@example.com>
License: MIT
Keywords: interceptor,nuitka,asyncuvkit
Classifier: Development Status :: 3 - Alpha
Classifier: Intended Audience :: Developers
Classifier: License :: OSI Approved :: MIT License
Classifier: Programming Language :: Python :: 3.8
Classifier: Operating System :: OS Independent
Classifier: Topic :: Software Development :: Libraries :: Python Modules
Requires-Python: <3.12,>=3.11
Requires-Dist: scikit-learn>=1.7.2
